appendzip/__init__.py
appendzip/appendzip.py
appendzip-0.1.1.dist-info/licenses/LICENSE.txt
appendzip-0.1.1.dist-info/METADATA
appendzip-0.1.1.dist-info/WHEEL
appendzip-0.1.1.dist-info/top_level.txt
appendzip-0.1.1.dist-info/RECORD
