Metadata-Version: 2.4
Name: appendzip
Version: 0.1.1
Summary: Append a single file to zip, overwriting the existing file if necessary
Home-page: https://github.com/barakplasma/append-zip
Author: Michael Salaverry
Author-email: barakplasma@gmail.com
Project-URL: Bug Tracker, https://github.com/barakplasma/append-zip/issues
Classifier: Programming Language :: Python :: 3
Classifier: License :: OSI Approved :: MIT License
Classifier: Operating System :: OS Independent
Requires-Python: >=3.6
License-File: LICENSE.txt
Provides-Extra: dev
Requires-Dist: check-manifest; extra == "dev"
Provides-Extra: test
Requires-Dist: coverage; extra == "test"
Dynamic: license-file
